LICENSE.txt
MANIFEST.in
README.rst
setup.py
silverberg/__init__.py
silverberg/client.py
silverberg/cluster.py
silverberg/lock.py
silverberg/locks.py
silverberg/logger.py
silverberg/marshal.py
silverberg/thrift_client.py
silverberg.egg-info/PKG-INFO
silverberg.egg-info/SOURCES.txt
silverberg.egg-info/dependency_links.txt
silverberg.egg-info/requires.txt
silverberg.egg-info/top_level.txt
silverberg/cassandra/Cassandra.py
silverberg/cassandra/__init__.py
silverberg/cassandra/constants.py
silverberg/cassandra/ttypes.py
silverberg/test/__init__.py
silverberg/test/test_client.py
silverberg/test/test_cluster.py
silverberg/test/test_lock.py
silverberg/test/test_logger.py
silverberg/test/test_marshal.py
silverberg/test/test_thrift_client.py
silverberg/test/util.py