Metadata-Version: 1.0
Name: silverberg
Version: 0.1.9
Summary: Twisted CQL Cassandra Client
Home-page: https://github.com/rackerlabs/silverberg/
Author: Ken Wronkiewicz
Author-email: ken.wronkiewicz@rackspace.com
License: APL2
Platform: UNKNOWN
Classifier: Development Status :: 4 - Beta
Classifier: License :: OSI Approved :: Apache Software License
Classifier: Programming Language :: Python :: 2.7
Classifier: Framework :: Twisted
